go_metrics/__init__.py
go_metrics/server.py
go_metrics/metrics/__init__.py
go_metrics/metrics/base.py
go_metrics/metrics/dummy.py
go_metrics/metrics/graphite.py
go_metrics/metrics/graphite_time_parser.py
go_metrics/metrics/tests/__init__.py
go_metrics/metrics/tests/test_dummy.py
go_metrics/metrics/tests/test_graphite.py
go_metrics/metrics/tests/test_graphite_time_parser.py
go_metrics/tests/__init__.py
go_metrics/tests/test_server.py
go_metrics_api-0.2.0.dist-info/DESCRIPTION.rst
go_metrics_api-0.2.0.dist-info/METADATA
go_metrics_api-0.2.0.dist-info/RECORD
go_metrics_api-0.2.0.dist-info/WHEEL
go_metrics_api-0.2.0.dist-info/metadata.json
go_metrics_api-0.2.0.dist-info/top_level.txt
