Metadata-Version: 2.0
Name: go-metrics-api
Version: 0.2.0
Summary: An API for querying vumi-go metrics
Home-page: http://github.com/praekelt/go-metrics-api
Author: Praekelt Foundation
Author-email: dev@praekeltfoundation.org
License: BSD
Platform: UNKNOWN
Classifier: Development Status :: 4 - Beta
Classifier: Intended Audience :: Developers
Classifier: License :: OSI Approved :: BSD License
Classifier: Operating System :: POSIX
Classifier: Programming Language :: Python
Classifier: Topic :: Software Development :: Libraries :: Python Modules
Classifier: Topic :: Internet :: WWW/HTTP
Requires-Dist: confmodel (==0.2.0)
Requires-Dist: cyclone
Requires-Dist: go-api (>=0.2.0)
Requires-Dist: pyasn1
Requires-Dist: treq
Requires-Dist: vumi (>=0.5.21)
